pyegctl/__init__.py
pyegctl/device.py
pyegctl-1.0.1.dist-info/LICENSE
pyegctl-1.0.1.dist-info/METADATA
pyegctl-1.0.1.dist-info/WHEEL
pyegctl-1.0.1.dist-info/top_level.txt
pyegctl-1.0.1.dist-info/RECORD
