Metadata-Version: 2.1
Name: pyegctl
Version: 1.0.1
Summary: Energenie control utility
Home-page: https://github.com/pzbbole/pyenergenie
Author: Michal Drzymala
Author-email: pzbbole@gmail.com
License: UNKNOWN
Platform: UNKNOWN
Classifier: Programming Language :: Python :: 3
Classifier: License :: OSI Approved :: MIT License
Classifier: Operating System :: OS Independent
Requires-Python: >=3.6
